redsage/__init__.py
redsage/cli.py
redsage/__pycache__/__init__.cpython-312.pyc
redsage/__pycache__/cli.cpython-312.pyc
redsage/core/agent.py
redsage/core/context.py
redsage/core/watcher.py
redsage/core/__pycache__/agent.cpython-312.pyc
redsage/core/__pycache__/watcher.cpython-312.pyc
redsage/llm/base.py
redsage/llm/claude.py
redsage/llm/openai.py
redsage/llm/__pycache__/base.cpython-312.pyc
redsage/llm/__pycache__/claude.cpython-312.pyc
redsage/llm/__pycache__/openai.cpython-312.pyc
redsage/utils/config.py
redsage/utils/git.py
redsage/utils/__pycache__/config.cpython-312.pyc
redsage/utils/__pycache__/git.cpython-312.pyc
redsage-0.1.1.dist-info/LICENSE
redsage-0.1.1.dist-info/METADATA
redsage-0.1.1.dist-info/WHEEL
redsage-0.1.1.dist-info/entry_points.txt
redsage-0.1.1.dist-info/top_level.txt
redsage-0.1.1.dist-info/RECORD
