Metadata-Version: 2.1
Name: redsage
Version: 0.1.1
Summary: A minimal terminal pair programmer
Author-email: Warren Chisasa <warrenchisasa@gmail.com>
License: MIT License
Project-URL: Homepage, https://github.com/chisasaw/redsage
Project-URL: Repository, https://github.com/chisasaw/redsage
Keywords: ai,pair-programming,llm,coding-assistant
Classifier: Development Status :: 3 - Alpha
Classifier: Intended Audience :: Developers
Classifier: License :: OSI Approved :: MIT License
Classifier: Programming Language :: Python :: 3.8
Classifier: Programming Language :: Python :: 3.9
Classifier: Programming Language :: Python :: 3.10
Requires-Python: >=3.8
License-File: LICENSE
Requires-Dist: watchdog>=2.1.6
Requires-Dist: click>=8.0.0
Requires-Dist: anthropic>=0.3.0
Requires-Dist: openai>=1.0.0
Requires-Dist: pyyaml>=5.4.1
Requires-Dist: gitpython>=3.1.0
Requires-Dist: prompt_toolkit>=3.0.0
